pya3rt/__init__.py
pya3rt/client.py
pya3rt/image_influence.py
pya3rt/listing.py
pya3rt/proofreading.py
pya3rt/talk.py
pya3rt/text_classification.py
pya3rt/text_suggest.py
pya3rt-1.1.dist-info/DESCRIPTION.rst
pya3rt-1.1.dist-info/METADATA
pya3rt-1.1.dist-info/RECORD
pya3rt-1.1.dist-info/WHEEL
pya3rt-1.1.dist-info/metadata.json
pya3rt-1.1.dist-info/top_level.txt
