Metadata-Version: 2.0
Name: pya3rt
Version: 1.1
Summary: A python wrapper for A3RT API
Home-page: https://github.com/nocotan/pya3rt
Author: nocotan
Author-email: UNKNOWN
License: MIT
Platform: UNKNOWN
Requires-Dist: requests (==2.12.4)
